simulcrypt/CWG.py
simulcrypt/MUX.py
simulcrypt/SCS.py
simulcrypt/__init__.py
simulcrypt/message.py
simulcrypt/mux_simulator.py
simulcrypt/parameters.py
simulcrypt/scs_simulator.py
simulcrypt/smdecode.py
simulcrypt/specification.py
simulcrypt-0.1.0.dist-info/METADATA
simulcrypt-0.1.0.dist-info/WHEEL
simulcrypt-0.1.0.dist-info/entry_points.txt
simulcrypt-0.1.0.dist-info/licenses/LICENSE.txt
simulcrypt-0.1.0.dist-info/RECORD
