Metadata-Version: 2.4
Name: simulcrypt
Version: 0.1.0
Summary: DVB Simulcrypt protocol messages encode/decode library, pure Python implementation.
Project-URL: Homepage, https://github.com/v5tepanov/simulcrypt
Project-URL: Issues, https://github.com/v5tepanov/simulcrypt/issues
Author-email: Victor Stepanov <v5tepanov@mail.ru>
License-File: LICENSE.txt
Classifier: License :: OSI Approved :: Apache Software License
Classifier: Operating System :: OS Independent
Classifier: Programming Language :: Python :: 3
Requires-Python: >=3.11
